{"web":{"client_id":"112614494687-bjtdrhokc4omsum1bovtp5l0l5i8n2n2.apps.googleusercontent.com","project_id":"central-apex-438817-p5","auth_uri":"https://accounts.google.com/o/oauth2/auth","token_uri":"https://oauth2.googleapis.com/token","auth_provider_x509_cert_url":"https://www.googleapis.com/oauth2/v1/certs","client_secret":"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","redirect_uris":["https://appdata-stg3-112614494687.europe-west9.run.app"],"javascript_origins":["https://appdata-stg3-112614494687.europe-west9.run.app"]}}